{
  "version": "1",
  "cognitoConfig": {
    "resourceNameTruncated": "awsampd687a6c0",
    "userPoolName": "users",
    "autoVerifiedAttributes": [
      "email"
    ],
    "mfaConfiguration": "OFF",
    "mfaTypes": [
      "SMS Text Message"
    ],
    "smsAuthenticationMessage": "Your authentication code is {####}",
    "smsVerificationMessage": "Your verification code is {####}",
    "emailVerificationSubject": "Código de Verificación",
    "emailVerificationMessage": "Su código es '{####}'.",
    "defaultPasswordPolicy": true,
    "passwordPolicyMinLength": "12",
    "passwordPolicyCharacters": [
      "Requires Lowercase",
      "Requires Uppercase",
      "Requires Numbers",
      "Requires Symbols"
    ],
    "requiredAttributes": [
      "email",
      "name"
    ],
    "aliasAttributes": [],
    "userpoolClientGenerateSecret": false,
    "userpoolClientRefreshTokenValidity": 30,
    "userpoolClientWriteAttributes": [
      "updated_at",
      "email",
      "name"
    ],
    "userpoolClientReadAttributes": [
      "email",
      "name",
      "updated_at"
    ],
    "userpoolClientLambdaRole": "usersd687a6c0_userpoolclient_lambda_role",
    "userpoolClientSetAttributes": true,
    "sharedId": "d687a6c0",
    "resourceName": "users",
    "authSelections": "userPoolOnly",
    "useDefault": "manual",
    "usernameAttributes": [
      "email"
    ],
    "userPoolGroups": true,
    "adminQueries": true,
    "triggers": {
      "DefineAuthChallenge": [
        "captcha-define-challenge"
      ],
      "CreateAuthChallenge": [
        "captcha-create-challenge"
      ],
      "VerifyAuthChallengeResponse": [
        "captcha-verify"
      ],
      "CustomMessage": [
        "verification-link"
      ]
    },
    "hostedUI": false,
    "userPoolGroupList": [
      "generalAdmin",
      "admin",
      "user"
    ],
    "serviceName": "Cognito",
    "verificationBucketName": "usersverificationbucket",
    "usernameCaseSensitive": false,
    "useEnabledMfas": true
  }
}